aigroup_video_mcp/__init__.py
aigroup_video_mcp/main.py
aigroup_video_mcp/settings.py
aigroup_video_mcp/core/__init__.py
aigroup_video_mcp/core/analyzer.py
aigroup_video_mcp/resources/__init__.py
aigroup_video_mcp/resources/base.py
aigroup_video_mcp/resources/config.py
aigroup_video_mcp/resources/models.py
aigroup_video_mcp/resources/status.py
aigroup_video_mcp/resources/usage_stats.py
aigroup_video_mcp/server/__init__.py
aigroup_video_mcp/server/mcp_server.py
aigroup_video_mcp/tools/__init__.py
aigroup_video_mcp/tools/analyze_custom.py
aigroup_video_mcp/tools/analyze_scenes.py
aigroup_video_mcp/tools/analyze_video.py
aigroup_video_mcp/tools/base.py
aigroup_video_mcp/tools/summarize_video.py
aigroup_video_mcp/tools/validate_source.py
aigroup_video_mcp-1.1.1.dist-info/licenses/LICENSE
aigroup_video_mcp-1.1.1.dist-info/METADATA
aigroup_video_mcp-1.1.1.dist-info/WHEEL
aigroup_video_mcp-1.1.1.dist-info/entry_points.txt
aigroup_video_mcp-1.1.1.dist-info/top_level.txt
aigroup_video_mcp-1.1.1.dist-info/RECORD
