Metadata-Version: 2.4
Name: aigroup-video-mcp
Version: 1.1.1
Summary: A MCP server for video multimodal understanding based on Alibaba Cloud DashScope
Author-email: Aigroup Team <team@aigroup.com>
License: MIT
Project-URL: Homepage, https://github.com/aigroup/aigroup-video-mcp
Project-URL: Documentation, https://github.com/aigroup/aigroup-video-mcp#readme
Project-URL: Repository, https://github.com/aigroup/aigroup-video-mcp
Project-URL: Bug Tracker, https://github.com/aigroup/aigroup-video-mcp/issues
Keywords: mcp,video,ai,dashscope,multimodal
Classifier: Development Status :: 4 - Beta
Classifier: Intended Audience :: Developers
Classifier: License :: OSI Approved :: MIT License
Classifier: Programming Language :: Python :: 3
Classifier: Programming Language :: Python :: 3.8
Classifier: Programming Language :: Python :: 3.9
Classifier: Programming Language :: Python :: 3.10
Classifier: Programming Language :: Python :: 3.11
Classifier: Programming Language :: Python :: 3.12
Classifier: Topic :: Software Development :: Libraries :: Python Modules
Classifier: Topic :: Scientific/Engineering :: Artificial Intelligence
Requires-Python: >=3.8
License-File: LICENSE
Requires-Dist: mcp>=1.0.0
Requires-Dist: dashscope>=1.14.0
Requires-Dist: pydantic>=2.0.0
Requires-Dist: fastapi>=0.100.0
Requires-Dist: loguru>=0.7.0
Requires-Dist: httpx>=0.24.0
Requires-Dist: aiofiles>=23.0.0
Requires-Dist: python-dotenv>=1.0.0
Requires-Dist: typing-extensions>=4.0.0
Requires-Dist: pydantic-settings>=2.0.0
Requires-Dist: psutil>=5.9.0
Provides-Extra: dev
Requires-Dist: pytest>=7.0.0; extra == "dev"
Requires-Dist: pytest-asyncio>=0.21.0; extra == "dev"
Requires-Dist: black>=23.0.0; extra == "dev"
Requires-Dist: isort>=5.12.0; extra == "dev"
Requires-Dist: mypy>=1.0.0; extra == "dev"
Dynamic: license-file
